<?xml version="1.0" encoding="UTF-8"?>

<!-- generated on 10/30/20 17:58:51 by Eclipse SUMO Version 1.6.0
<configuration xmlns:xsi="http://www.w3.org/2001/XMLSchema-instance" xsi:noNamespaceSchemaLocation="http://sumo.dlr.de/xsd/sumoConfiguration.xsd">

    <input>
        <net-file value="env/3x3/in-out.net.xml"/>
        <route-files value="env/3x3/in-out.rou.xml"/>
        <additional-files value="env/3x3/../output-config.xml"/>
    </input>

    <output>
        <output-prefix value="3x3/output/fixedtime/"/>
    </output>

    <time>
        <begin value="0"/>
        <end value="5400"/>
    </time>

    <processing>
        <time-to-teleport value="-1"/>
    </processing>

    <traci_server>
        <remote-port value="12797"/>
    </traci_server>

    <gui_only>
        <start value="true"/>
    </gui_only>

</configuration>
-->

<meandata xmlns:xsi="http://www.w3.org/2001/XMLSchema-instance" xsi:noNamespaceSchemaLocation="http://sumo.dlr.de/xsd/meandata_file.xsd">
    <interval begin="0.00" end="900.00" id="15min-lane">
        <edge id="A0A1">
            <lane id="A0A1_0" sampledSeconds="0.00" departed="0" arrived="0" entered="0" left="0" laneChangedFrom="0" laneChangedTo="0"/>
            <lane id="A0A1_1" sampledSeconds="0.00" departed="0" arrived="0" entered="0" left="0" laneChangedFrom="0" laneChangedTo="0"/>
            <lane id="A0A1_2" sampledSeconds="0.00" departed="0" arrived="0" entered="0" left="0" laneChangedFrom="0" laneChangedTo="0"/>
            <lane id="A0A1_3" sampledSeconds="0.00" departed="0" arrived="0" entered="0" left="0" laneChangedFrom="0" laneChangedTo="0"/>
        </edge>
        <edge id="A0B0">
            <lane id="A0B0_0" sampledSeconds="686.77" traveltime="10.01" overlapTraveltime="10.34" density="6.56" laneDensity="6.56" occupancy="3.18" waitingTime="259.00" speed="11.74" departed="0" arrived="0" entered="66" left="70" laneChangedFrom="0" laneChangedTo="4"/>
            <lane id="A0B0_1" sampledSeconds="602.77" traveltime="8.43" overlapTraveltime="8.79" density="5.75" laneDensity="5.75" occupancy="2.77" waitingTime="163.00" speed="13.81" departed="0" arrived="0" entered="70" left="70" laneChangedFrom="5" laneChangedTo="6"/>
            <lane id="A0B0_2" sampledSeconds="621.00" traveltime="8.49" overlapTraveltime="8.72" density="5.93" laneDensity="5.93" occupancy="2.87" waitingTime="194.00" speed="13.91" departed="0" arrived="0" entered="72" left="69" laneChangedFrom="8" laneChangedTo="5"/>
            <lane id="A0B0_3" sampledSeconds="590.02" traveltime="6.42" overlapTraveltime="6.61" density="5.63" laneDensity="5.63" occupancy="2.71" waitingTime="87.00" speed="18.35" departed="0" arrived="0" entered="88" left="86" laneChangedFrom="4" laneChangedTo="2"/>
        </edge>
        <edge id="A0bottom0">
            <lane id="A0bottom0_0" sampledSeconds="403.20" traveltime="5.62" overlapTraveltime="5.80" density="3.36" laneDensity="3.36" occupancy="1.62" waitingTime="0.00" speed="23.84" departed="0" arrived="70" entered="69" left="0" laneChangedFrom="0" laneChangedTo="1"/>
            <lane id="A0bottom0_1" sampledSeconds="370.81" traveltime="5.82" overlapTraveltime="6.00" density="3.09" laneDensity="3.09" occupancy="1.49" waitingTime="0.00" speed="23.04" departed="0" arrived="62" entered="62" left="0" laneChangedFrom="1" laneChangedTo="1"/>
            <lane id="A0bottom0_2" sampledSeconds="435.63" traveltime="5.74" overlapTraveltime="5.91" density="3.63" laneDensity="3.63" occupancy="1.75" waitingTime="0.00" speed="23.37" departed="0" arrived="75" entered="73" left="0" laneChangedFrom="1" laneChangedTo="3"/>
            <lane id="A0bottom0_3" sampledSeconds="425.69" traveltime="5.50" overlapTraveltime="5.67" density="3.55" laneDensity="3.55" occupancy="1.71" waitingTime="0.00" speed="24.37" departed="0" arrived="74" entered="77" left="0" laneChangedFrom="3" laneChangedTo="0"/>
        </edge>
        <edge id="A0left0">
            <lane id="A0left0_0" sampledSeconds="0.00" departed="0" arrived="0" entered="0" left="0" laneChangedFrom="0" laneChangedTo="0"/>
            <lane id="A0left0_1" sampledSeconds="0.00" departed="0" arrived="0" entered="0" left="0" laneChangedFrom="0" laneChangedTo="0"/>
            <lane id="A0left0_2" sampledSeconds="0.00" departed="0" arrived="0" entered="0" left="0" laneChangedFrom="0" laneChangedTo="0"/>
            <lane id="A0left0_3" sampledSeconds="0.00" departed="0" arrived="0" entered="0" left="0" laneChangedFrom="0" laneChangedTo="0"/>
        </edge>
        <edge id="A1A0">
            <lane id="A1A0_0" sampledSeconds="442.45" traveltime="6.06" overlapTraveltime="6.41" density="4.22" laneDensity="4.22" occupancy="2.02" waitingTime="0.00" speed="18.93" departed="0" arrived="0" entered="68" left="69" laneChangedFrom="0" laneChangedTo="1"/>
            <lane id="A1A0_1" sampledSeconds="419.86" traveltime="6.34" overlapTraveltime="6.70" density="4.01" laneDensity="4.01" occupancy="1.92" waitingTime="0.00" speed="18.11" departed="0" arrived="0" entered="64" left="62" laneChangedFrom="2" laneChangedTo="0"/>
            <lane id="A1A0_2" sampledSeconds="486.76" traveltime="6.40" overlapTraveltime="6.76" density="4.65" laneDensity="4.65" occupancy="2.23" waitingTime="0.00" speed="17.95" departed="0" arrived="0" entered="71" left="72" laneChangedFrom="1" laneChangedTo="2"/>
            <lane id="A1A0_3" sampledSeconds="543.79" traveltime="6.65" overlapTraveltime="7.02" density="5.19" laneDensity="5.19" occupancy="2.49" waitingTime="0.00" speed="17.28" departed="0" arrived="0" entered="78" left="78" laneChangedFrom="1" laneChangedTo="1"/>
        </edge>
        <edge id="A1A2">
            <lane id="A1A2_0" sampledSeconds="0.00" departed="0" arrived="0" entered="0" left="0" laneChangedFrom="0" laneChangedTo="0"/>
            <lane id="A1A2_1" sampledSeconds="0.00" departed="0" arrived="0" entered="0" left="0" laneChangedFrom="0" laneChangedTo="0"/>
            <lane id="A1A2_2" sampledSeconds="0.00" departed="0" arrived="0" entered="0" left="0" laneChangedFrom="0" laneChangedTo="0"/>
            <lane id="A1A2_3" sampledSeconds="0.00" departed="0" arrived="0" entered="0" left="0" laneChangedFrom="0" laneChangedTo="0"/>
        </edge>
        <edge id="A1B1">
            <lane id="A1B1_0" sampledSeconds="581.95" traveltime="8.53" overlapTraveltime="8.86" density="5.56" laneDensity="5.56" occupancy="2.68" waitingTime="169.00" speed="13.71" departed="0" arrived="0" entered="65" left="68" laneChangedFrom="1" laneChangedTo="5"/>
            <lane id="A1B1_1" sampledSeconds="634.44" traveltime="8.20" overlapTraveltime="8.44" density="6.06" laneDensity="6.06" occupancy="2.93" waitingTime="186.00" speed="14.38" departed="0" arrived="0" entered="76" left="76" laneChangedFrom="6" laneChangedTo="6"/>
            <lane id="A1B1_2" sampledSeconds="549.89" traveltime="7.44" overlapTraveltime="7.67" density="5.25" laneDensity="5.25" occupancy="2.53" waitingTime="115.00" speed="15.82" departed="0" arrived="0" entered="72" left="68" laneChangedFrom="5" laneChangedTo="2"/>
            <lane id="A1B1_3" sampledSeconds="554.28" traveltime="6.48" overlapTraveltime="6.70" density="5.29" laneDensity="5.29" occupancy="2.54" waitingTime="79.00" speed="18.12" departed="0" arrived="0" entered="83" left="82" laneChangedFrom="1" laneChangedTo="0"/>
        </edge>
        <edge id="A1left1">
            <lane id="A1left1_0" sampledSeconds="0.00" departed="0" arrived="0" entered="0" left="0" laneChangedFrom="0" laneChangedTo="0"/>
            <lane id="A1left1_1" sampledSeconds="0.00" departed="0" arrived="0" entered="0" left="0" laneChangedFrom="0" laneChangedTo="0"/>
            <lane id="A1left1_2" sampledSeconds="0.00" departed="0" arrived="0" entered="0" left="0" laneChangedFrom="0" laneChangedTo="0"/>
            <lane id="A1left1_3" sampledSeconds="0.00" departed="0" arrived="0" entered="0" left="0" laneChangedFrom="0" laneChangedTo="0"/>
        </edge>
        <edge id="A2A1">
            <lane id="A2A1_0" sampledSeconds="381.64" traveltime="5.42" overlapTraveltime="5.61" density="3.64" laneDensity="3.64" occupancy="1.74" waitingTime="0.00" speed="21.63" departed="0" arrived="0" entered="68" left="68" laneChangedFrom="0" laneChangedTo="0"/>
            <lane id="A2A1_1" sampledSeconds="371.43" traveltime="5.59" overlapTraveltime="5.78" density="3.55" laneDensity="3.55" occupancy="1.69" waitingTime="0.00" speed="20.99" departed="0" arrived="0" entered="65" left="63" laneChangedFrom="2" laneChangedTo="0"/>
            <lane id="A2A1_2" sampledSeconds="401.67" traveltime="5.47" overlapTraveltime="5.66" density="3.83" laneDensity="3.83" occupancy="1.83" waitingTime="0.00" speed="21.44" departed="0" arrived="0" entered="71" left="72" laneChangedFrom="1" laneChangedTo="2"/>
            <lane id="A2A1_3" sampledSeconds="432.06" traveltime="5.36" overlapTraveltime="5.55" density="4.12" laneDensity="4.12" occupancy="1.97" waitingTime="0.00" speed="21.88" departed="0" arrived="0" entered="77" left="78" laneChangedFrom="0" laneChangedTo="1"/>
        </edge>
        <edge id="A2B2">
            <lane id="A2B2_0" sampledSeconds="387.06" traveltime="5.52" overlapTraveltime="5.72" density="3.69" laneDensity="3.69" occupancy="1.77" waitingTime="0.00" speed="21.24" departed="0" arrived="0" entered="69" left="67" laneChangedFrom="2" laneChangedTo="0"/>
            <lane id="A2B2_1" sampledSeconds="381.07" traveltime="5.73" overlapTraveltime="5.92" density="3.64" laneDensity="3.64" occupancy="1.74" waitingTime="0.00" speed="20.49" departed="0" arrived="0" entered="64" left="65" laneChangedFrom="1" laneChangedTo="2"/>
            <lane id="A2B2_2" sampledSeconds="470.08" traveltime="5.45" overlapTraveltime="5.64" density="4.49" laneDensity="4.49" occupancy="2.15" waitingTime="0.00" speed="21.54" departed="0" arrived="0" entered="83" left="83" laneChangedFrom="0" laneChangedTo="1"/>
            <lane id="A2B2_3" sampledSeconds="443.02" traveltime="5.35" overlapTraveltime="5.54" density="4.23" laneDensity="4.23" occupancy="2.02" waitingTime="0.00" speed="21.92" departed="0" arrived="0" entered="80" left="80" laneChangedFrom="0" laneChangedTo="0"/>
        </edge>
        <edge id="A2left2">
            <lane id="A2left2_0" sampledSeconds="0.00" departed="0" arrived="0" entered="0" left="0" laneChangedFrom="0" laneChangedTo="0"/>
            <lane id="A2left2_1" sampledSeconds="0.00" departed="0" arrived="0" entered="0" left="0" laneChangedFrom="0" laneChangedTo="0"/>
            <lane id="A2left2_2" sampledSeconds="0.00" departed="0" arrived="0" entered="0" left="0" laneChangedFrom="0" laneChangedTo="0"/>
            <lane id="A2left2_3" sampledSeconds="0.00" departed="0" arrived="0" entered="0" left="0" laneChangedFrom="0" laneChangedTo="0"/>
        </edge>
        <edge id="A2top0">
            <lane id="A2top0_0" sampledSeconds="0.00" departed="0" arrived="0" entered="0" left="0" laneChangedFrom="0" laneChangedTo="0"/>
            <lane id="A2top0_1" sampledSeconds="0.00" departed="0" arrived="0" entered="0" left="0" laneChangedFrom="0" laneChangedTo="0"/>
            <lane id="A2top0_2" sampledSeconds="0.00" departed="0" arrived="0" entered="0" left="0" laneChangedFrom="0" laneChangedTo="0"/>
            <lane id="A2top0_3" sampledSeconds="0.00" departed="0" arrived="0" entered="0" left="0" laneChangedFrom="0" laneChangedTo="0"/>
        </edge>
        <edge id="B0A0">
            <lane id="B0A0_0" sampledSeconds="0.00" departed="0" arrived="0" entered="0" left="0" laneChangedFrom="0" laneChangedTo="0"/>
            <lane id="B0A0_1" sampledSeconds="0.00" departed="0" arrived="0" entered="0" left="0" laneChangedFrom="0" laneChangedTo="0"/>
            <lane id="B0A0_2" sampledSeconds="0.00" departed="0" arrived="0" entered="0" left="0" laneChangedFrom="0" laneChangedTo="0"/>
            <lane id="B0A0_3" sampledSeconds="0.00" departed="0" arrived="0" entered="0" left="0" laneChangedFrom="0" laneChangedTo="0"/>
        </edge>
        <edge id="B0B1">
            <lane id="B0B1_0" sampledSeconds="0.00" departed="0" arrived="0" entered="0" left="0" laneChangedFrom="0" laneChangedTo="0"/>
            <lane id="B0B1_1" sampledSeconds="0.00" departed="0" arrived="0" entered="0" left="0" laneChangedFrom="0" laneChangedTo="0"/>
            <lane id="B0B1_2" sampledSeconds="0.00" departed="0" arrived="0" entered="0" left="0" laneChangedFrom="0" laneChangedTo="0"/>
            <lane id="B0B1_3" sampledSeconds="0.00" departed="0" arrived="0" entered="0" left="0" laneChangedFrom="0" laneChangedTo="0"/>
        </edge>
        <edge id="B0C0">
            <lane id="B0C0_0" sampledSeconds="389.37" traveltime="5.38" overlapTraveltime="5.57" density="3.72" laneDensity="3.72" occupancy="1.79" waitingTime="76.00" speed="21.80" departed="0" arrived="0" entered="70" left="69" laneChangedFrom="0" laneChangedTo="0"/>
            <lane id="B0C0_1" sampledSeconds="389.50" traveltime="5.12" overlapTraveltime="5.31" density="3.72" laneDensity="3.72" occupancy="1.79" waitingTime="62.00" speed="22.84" departed="0" arrived="0" entered="73" left="75" laneChangedFrom="0" laneChangedTo="2"/>
            <lane id="B0C0_2" sampledSeconds="326.86" traveltime="4.73" overlapTraveltime="4.90" density="3.12" laneDensity="3.12" occupancy="1.51" waitingTime="54.00" speed="24.79" departed="0" arrived="0" entered="65" left="66" laneChangedFrom="2" laneChangedTo="4"/>
            <lane id="B0C0_3" sampledSeconds="536.07" traveltime="6.21" overlapTraveltime="6.43" density="5.12" laneDensity="5.12" occupancy="2.48" waitingTime="190.00" speed="18.87" departed="0" arrived="0" entered="86" left="81" laneChangedFrom="4" laneChangedTo="0"/>
        </edge>
        <edge id="B0bottom1">
            <lane id="B0bottom1_0" sampledSeconds="499.11" traveltime="3.69" overlapTraveltime="3.82" density="4.16" laneDensity="4.16" occupancy="2.01" waitingTime="0.00" speed="36.21" departed="0" arrived="131" entered="131" left="0" laneChangedFrom="0" laneChangedTo="0"/>
            <lane id="B0bottom1_1" sampledSeconds="554.47" traveltime="3.58" overlapTraveltime="3.71" density="4.63" laneDensity="4.63" occupancy="2.23" waitingTime="0.00" speed="37.27" departed="0" arrived="150" entered="150" left="0" laneChangedFrom="0" laneChangedTo="0"/>
        </edge>
        <edge id="B1A1">
            <lane id="B1A1_0" sampledSeconds="0.00" departed="0" arrived="0" entered="0" left="0" laneChangedFrom="0" laneChangedTo="0"/>
            <lane id="B1A1_1" sampledSeconds="0.00" departed="0" arrived="0" entered="0" left="0" laneChangedFrom="0" laneChangedTo="0"/>
            <lane id="B1A1_2" sampledSeconds="0.00" departed="0" arrived="0" entered="0" left="0" laneChangedFrom="0" laneChangedTo="0"/>
            <lane id="B1A1_3" sampledSeconds="0.00" departed="0" arrived="0" entered="0" left="0" laneChangedFrom="0" laneChangedTo="0"/>
        </edge>
        <edge id="B1B0">
            <lane id="B1B0_0" sampledSeconds="0.00" departed="0" arrived="0" entered="0" left="0" laneChangedFrom="0" laneChangedTo="0"/>
            <lane id="B1B0_1" sampledSeconds="586.85" traveltime="4.32" overlapTraveltime="4.48" density="5.60" laneDensity="5.60" occupancy="2.68" waitingTime="0.00" speed="27.08" departed="0" arrived="0" entered="130" left="131" laneChangedFrom="0" laneChangedTo="1"/>
            <lane id="B1B0_2" sampledSeconds="647.59" traveltime="4.16" overlapTraveltime="4.31" density="6.18" laneDensity="6.18" occupancy="2.96" waitingTime="0.00" speed="28.14" departed="0" arrived="0" entered="151" left="150" laneChangedFrom="1" laneChangedTo="0"/>
            <lane id="B1B0_3" sampledSeconds="0.00" departed="0" arrived="0" entered="0" left="0" laneChangedFrom="0" laneChangedTo="0"/>
        </edge>
        <edge id="B1B2">
            <lane id="B1B2_0" sampledSeconds="0.00" departed="0" arrived="0" entered="0" left="0" laneChangedFrom="0" laneChangedTo="0"/>
            <lane id="B1B2_1" sampledSeconds="0.00" departed="0" arrived="0" entered="0" left="0" laneChangedFrom="0" laneChangedTo="0"/>
            <lane id="B1B2_2" sampledSeconds="0.00" departed="0" arrived="0" entered="0" left="0" laneChangedFrom="0" laneChangedTo="0"/>
            <lane id="B1B2_3" sampledSeconds="0.00" departed="0" arrived="0" entered="0" left="0" laneChangedFrom="0" laneChangedTo="0"/>
        </edge>
        <edge id="B1C1">
            <lane id="B1C1_0" sampledSeconds="423.99" traveltime="6.00" overlapTraveltime="6.22" density="4.05" laneDensity="4.05" occupancy="1.96" waitingTime="116.00" speed="19.52" departed="0" arrived="0" entered="68" left="69" laneChangedFrom="0" laneChangedTo="1"/>
            <lane id="B1C1_1" sampledSeconds="388.78" traveltime="4.94" overlapTraveltime="5.13" density="3.71" laneDensity="3.71" occupancy="1.79" waitingTime="75.00" speed="23.67" departed="0" arrived="0" entered="76" left="75" laneChangedFrom="1" laneChangedTo="0"/>
            <lane id="B1C1_2" sampledSeconds="317.58" traveltime="4.37" overlapTraveltime="4.53" density="3.03" laneDensity="3.03" occupancy="1.46" waitingTime="37.00" speed="26.78" departed="0" arrived="0" entered="68" left="72" laneChangedFrom="0" laneChangedTo="5"/>
            <lane id="B1C1_3" sampledSeconds="488.19" traveltime="5.92" overlapTraveltime="6.14" density="4.66" laneDensity="4.66" occupancy="2.26" waitingTime="156.00" speed="19.78" departed="0" arrived="0" entered="82" left="77" laneChangedFrom="5" laneChangedTo="0"/>
        </edge>
        <edge id="B2A2">
            <lane id="B2A2_0" sampledSeconds="0.00" departed="0" arrived="0" entered="0" left="0" laneChangedFrom="0" laneChangedTo="0"/>
            <lane id="B2A2_1" sampledSeconds="0.00" departed="0" arrived="0" entered="0" left="0" laneChangedFrom="0" laneChangedTo="0"/>
            <lane id="B2A2_2" sampledSeconds="0.00" departed="0" arrived="0" entered="0" left="0" laneChangedFrom="0" laneChangedTo="0"/>
            <lane id="B2A2_3" sampledSeconds="0.00" departed="0" arrived="0" entered="0" left="0" laneChangedFrom="0" laneChangedTo="0"/>
        </edge>
        <edge id="B2B1">
            <lane id="B2B1_0" sampledSeconds="68.99" traveltime="8.51" overlapTraveltime="8.88" density="0.66" laneDensity="0.66" occupancy="0.31" waitingTime="0.00" speed="13.67" departed="0" arrived="0" entered="23" left="0" laneChangedFrom="23" laneChangedTo="0"/>
            <lane id="B2B1_1" sampledSeconds="915.04" traveltime="7.48" overlapTraveltime="7.71" density="8.73" laneDensity="8.73" occupancy="4.18" waitingTime="0.00" speed="15.74" departed="0" arrived="0" entered="100" left="130" laneChangedFrom="3" laneChangedTo="33"/>
            <lane id="B2B1_2" sampledSeconds="1160.63" traveltime="8.08" overlapTraveltime="8.31" density="11.08" laneDensity="11.08" occupancy="5.29" waitingTime="0.00" speed="14.61" departed="0" arrived="0" entered="110" left="151" laneChangedFrom="11" laneChangedTo="52"/>
            <lane id="B2B1_3" sampledSeconds="144.35" traveltime="9.29" overlapTraveltime="9.69" density="1.38" laneDensity="1.38" occupancy="0.64" waitingTime="0.00" speed="12.53" departed="0" arrived="0" entered="48" left="0" laneChangedFrom="49" laneChangedTo="1"/>
        </edge>
        <edge id="B2C2">
            <lane id="B2C2_0" sampledSeconds="489.44" traveltime="7.00" overlapTraveltime="7.25" density="4.67" laneDensity="4.67" occupancy="2.27" waitingTime="185.00" speed="16.73" departed="0" arrived="0" entered="67" left="64" laneChangedFrom="4" laneChangedTo="2"/>
            <lane id="B2C2_1" sampledSeconds="610.86" traveltime="9.03" overlapTraveltime="9.35" density="5.83" laneDensity="5.83" occupancy="2.84" waitingTime="298.00" speed="12.98" departed="0" arrived="0" entered="65" left="70" laneChangedFrom="4" laneChangedTo="9"/>
            <lane id="B2C2_2" sampledSeconds="593.74" traveltime="6.99" overlapTraveltime="7.23" density="5.67" laneDensity="5.67" occupancy="2.75" waitingTime="230.00" speed="16.78" departed="0" arrived="0" entered="82" left="83" laneChangedFrom="5" laneChangedTo="6"/>
            <lane id="B2C2_3" sampledSeconds="598.67" traveltime="7.34" overlapTraveltime="7.60" density="5.71" laneDensity="5.71" occupancy="2.78" waitingTime="257.00" speed="15.97" departed="0" arrived="0" entered="80" left="76" laneChangedFrom="4" laneChangedTo="0"/>
        </edge>
        <edge id="B2top1">
            <lane id="B2top1_0" sampledSeconds="0.00" departed="0" arrived="0" entered="0" left="0" laneChangedFrom="0" laneChangedTo="0"/>
            <lane id="B2top1_1" sampledSeconds="0.00" departed="0" arrived="0" entered="0" left="0" laneChangedFrom="0" laneChangedTo="0"/>
            <lane id="B2top1_2" sampledSeconds="0.00" departed="0" arrived="0" entered="0" left="0" laneChangedFrom="0" laneChangedTo="0"/>
            <lane id="B2top1_3" sampledSeconds="0.00" departed="0" arrived="0" entered="0" left="0" laneChangedFrom="0" laneChangedTo="0"/>
        </edge>
        <edge id="C0B0">
            <lane id="C0B0_0" sampledSeconds="0.00" departed="0" arrived="0" entered="0" left="0" laneChangedFrom="0" laneChangedTo="0"/>
            <lane id="C0B0_1" sampledSeconds="0.00" departed="0" arrived="0" entered="0" left="0" laneChangedFrom="0" laneChangedTo="0"/>
            <lane id="C0B0_2" sampledSeconds="0.00" departed="0" arrived="0" entered="0" left="0" laneChangedFrom="0" laneChangedTo="0"/>
            <lane id="C0B0_3" sampledSeconds="0.00" departed="0" arrived="0" entered="0" left="0" laneChangedFrom="0" laneChangedTo="0"/>
        </edge>
        <edge id="C0C1">
            <lane id="C0C1_0" sampledSeconds="0.00" departed="0" arrived="0" entered="0" left="0" laneChangedFrom="0" laneChangedTo="0"/>
            <lane id="C0C1_1" sampledSeconds="0.00" departed="0" arrived="0" entered="0" left="0" laneChangedFrom="0" laneChangedTo="0"/>
            <lane id="C0C1_2" sampledSeconds="0.00" departed="0" arrived="0" entered="0" left="0" laneChangedFrom="0" laneChangedTo="0"/>
            <lane id="C0C1_3" sampledSeconds="0.00" departed="0" arrived="0" entered="0" left="0" laneChangedFrom="0" laneChangedTo="0"/>
        </edge>
        <edge id="C0bottom2">
            <lane id="C0bottom2_0" sampledSeconds="332.66" traveltime="5.99" overlapTraveltime="6.18" density="2.77" laneDensity="2.77" occupancy="1.34" waitingTime="0.00" speed="22.38" departed="0" arrived="54" entered="54" left="0" laneChangedFrom="0" laneChangedTo="0"/>
            <lane id="C0bottom2_1" sampledSeconds="415.58" traveltime="5.36" overlapTraveltime="5.53" density="3.47" laneDensity="3.47" occupancy="1.67" waitingTime="0.00" speed="24.99" departed="0" arrived="78" entered="74" left="0" laneChangedFrom="0" laneChangedTo="4"/>
            <lane id="C0bottom2_2" sampledSeconds="400.92" traveltime="5.50" overlapTraveltime="5.67" density="3.34" laneDensity="3.34" occupancy="1.61" waitingTime="0.00" speed="24.39" departed="0" arrived="69" entered="72" left="0" laneChangedFrom="4" laneChangedTo="1"/>
            <lane id="C0bottom2_3" sampledSeconds="426.14" traveltime="5.13" overlapTraveltime="5.30" density="3.55" laneDensity="3.55" occupancy="1.71" waitingTime="0.00" speed="26.10" departed="0" arrived="80" entered="81" left="0" laneChangedFrom="1" laneChangedTo="0"/>
        </edge>
        <edge id="C0right0">
            <lane id="C0right0_0" sampledSeconds="268.23" traveltime="3.68" overlapTraveltime="3.80" density="2.24" laneDensity="2.24" occupancy="1.08" waitingTime="0.00" speed="36.34" departed="0" arrived="71" entered="71" left="0" laneChangedFrom="0" laneChangedTo="1"/>
            <lane id="C0right0_1" sampledSeconds="271.11" traveltime="3.69" overlapTraveltime="3.82" density="2.26" laneDensity="2.26" occupancy="1.09" waitingTime="0.00" speed="36.17" departed="0" arrived="69" entered="72" left="0" laneChangedFrom="1" laneChangedTo="0"/>
            <lane id="C0right0_2" sampledSeconds="230.89" traveltime="3.47" overlapTraveltime="3.59" density="1.93" laneDensity="1.93" occupancy="0.93" waitingTime="0.00" speed="38.50" departed="0" arrived="65" entered="65" left="0" laneChangedFrom="0" laneChangedTo="2"/>
            <lane id="C0right0_3" sampledSeconds="290.08" traveltime="3.55" overlapTraveltime="3.67" density="2.42" laneDensity="2.42" occupancy="1.17" waitingTime="0.00" speed="37.67" departed="0" arrived="77" entered="80" left="0" laneChangedFrom="2" laneChangedTo="0"/>
        </edge>
        <edge id="C1B1">
            <lane id="C1B1_0" sampledSeconds="0.00" departed="0" arrived="0" entered="0" left="0" laneChangedFrom="0" laneChangedTo="0"/>
            <lane id="C1B1_1" sampledSeconds="0.00" departed="0" arrived="0" entered="0" left="0" laneChangedFrom="0" laneChangedTo="0"/>
            <lane id="C1B1_2" sampledSeconds="0.00" departed="0" arrived="0" entered="0" left="0" laneChangedFrom="0" laneChangedTo="0"/>
            <lane id="C1B1_3" sampledSeconds="0.00" departed="0" arrived="0" entered="0" left="0" laneChangedFrom="0" laneChangedTo="0"/>
        </edge>
        <edge id="C1C0">
            <lane id="C1C0_0" sampledSeconds="377.07" traveltime="6.56" overlapTraveltime="6.92" density="3.60" laneDensity="3.60" occupancy="1.73" waitingTime="0.00" speed="17.54" departed="0" arrived="0" entered="55" left="54" laneChangedFrom="1" laneChangedTo="0"/>
            <lane id="C1C0_1" sampledSeconds="459.85" traveltime="5.88" overlapTraveltime="6.21" density="4.39" laneDensity="4.39" occupancy="2.11" waitingTime="0.00" speed="19.56" departed="0" arrived="0" entered="74" left="74" laneChangedFrom="1" laneChangedTo="1"/>
            <lane id="C1C0_2" sampledSeconds="493.82" traveltime="6.36" overlapTraveltime="6.72" density="4.71" laneDensity="4.71" occupancy="2.26" waitingTime="0.00" speed="18.07" departed="0" arrived="0" entered="74" left="72" laneChangedFrom="3" laneChangedTo="1"/>
            <lane id="C1C0_3" sampledSeconds="495.83" traveltime="5.96" overlapTraveltime="6.28" density="4.73" laneDensity="4.73" occupancy="2.27" waitingTime="0.00" speed="19.33" departed="0" arrived="0" entered="78" left="81" laneChangedFrom="0" laneChangedTo="3"/>
        </edge>
        <edge id="C1C2">
            <lane id="C1C2_0" sampledSeconds="0.00" departed="0" arrived="0" entered="0" left="0" laneChangedFrom="0" laneChangedTo="0"/>
            <lane id="C1C2_1" sampledSeconds="0.00" departed="0" arrived="0" entered="0" left="0" laneChangedFrom="0" laneChangedTo="0"/>
            <lane id="C1C2_2" sampledSeconds="0.00" departed="0" arrived="0" entered="0" left="0" laneChangedFrom="0" laneChangedTo="0"/>
            <lane id="C1C2_3" sampledSeconds="0.00" departed="0" arrived="0" entered="0" left="0" laneChangedFrom="0" laneChangedTo="0"/>
        </edge>
        <edge id="C1right1">
            <lane id="C1right1_0" sampledSeconds="278.28" traveltime="3.72" overlapTraveltime="3.85" density="2.32" laneDensity="2.32" occupancy="1.12" waitingTime="0.00" speed="35.94" departed="0" arrived="73" entered="71" left="0" laneChangedFrom="0" laneChangedTo="2"/>
            <lane id="C1right1_1" sampledSeconds="262.98" traveltime="3.53" overlapTraveltime="3.65" density="2.19" laneDensity="2.19" occupancy="1.06" waitingTime="0.00" speed="37.86" departed="0" arrived="72" entered="73" left="0" laneChangedFrom="2" laneChangedTo="2"/>
            <lane id="C1right1_2" sampledSeconds="257.98" traveltime="3.46" overlapTraveltime="3.58" density="2.15" laneDensity="2.15" occupancy="1.04" waitingTime="0.00" speed="38.55" departed="0" arrived="73" entered="72" left="0" laneChangedFrom="2" laneChangedTo="3"/>
            <lane id="C1right1_3" sampledSeconds="274.80" traveltime="3.51" overlapTraveltime="3.63" density="2.29" laneDensity="2.29" occupancy="1.11" waitingTime="0.00" speed="38.04" departed="0" arrived="74" entered="77" left="0" laneChangedFrom="3" laneChangedTo="0"/>
        </edge>
        <edge id="C2B2">
            <lane id="C2B2_0" sampledSeconds="0.00" departed="0" arrived="0" entered="0" left="0" laneChangedFrom="0" laneChangedTo="0"/>
            <lane id="C2B2_1" sampledSeconds="0.00" departed="0" arrived="0" entered="0" left="0" laneChangedFrom="0" laneChangedTo="0"/>
            <lane id="C2B2_2" sampledSeconds="0.00" departed="0" arrived="0" entered="0" left="0" laneChangedFrom="0" laneChangedTo="0"/>
            <lane id="C2B2_3" sampledSeconds="0.00" departed="0" arrived="0" entered="0" left="0" laneChangedFrom="0" laneChangedTo="0"/>
        </edge>
        <edge id="C2C1">
            <lane id="C2C1_0" sampledSeconds="342.51" traveltime="5.99" overlapTraveltime="6.20" density="3.27" laneDensity="3.27" occupancy="1.56" waitingTime="0.00" speed="19.59" departed="0" arrived="0" entered="55" left="55" laneChangedFrom="1" laneChangedTo="1"/>
            <lane id="C2C1_1" sampledSeconds="413.54" traveltime="5.41" overlapTraveltime="5.60" density="3.95" laneDensity="3.95" occupancy="1.89" waitingTime="0.00" speed="21.67" departed="0" arrived="0" entered="75" left="74" laneChangedFrom="3" laneChangedTo="2"/>
            <lane id="C2C1_2" sampledSeconds="404.50" traveltime="5.42" overlapTraveltime="5.61" density="3.86" laneDensity="3.86" occupancy="1.84" waitingTime="0.00" speed="21.64" departed="0" arrived="0" entered="72" left="72" laneChangedFrom="3" laneChangedTo="3"/>
            <lane id="C2C1_3" sampledSeconds="432.12" traveltime="5.23" overlapTraveltime="5.41" density="4.12" laneDensity="4.12" occupancy="1.97" waitingTime="0.00" speed="22.42" departed="0" arrived="0" entered="79" left="80" laneChangedFrom="1" laneChangedTo="2"/>
        </edge>
        <edge id="C2right2">
            <lane id="C2right2_0" sampledSeconds="254.39" traveltime="3.78" overlapTraveltime="3.90" density="2.12" laneDensity="2.12" occupancy="1.02" waitingTime="0.00" speed="35.41" departed="0" arrived="66" entered="64" left="0" laneChangedFrom="0" laneChangedTo="2"/>
            <lane id="C2right2_1" sampledSeconds="293.80" traveltime="4.02" overlapTraveltime="4.15" density="2.45" laneDensity="2.45" occupancy="1.18" waitingTime="0.00" speed="33.31" departed="0" arrived="72" entered="71" left="0" laneChangedFrom="2" laneChangedTo="3"/>
            <lane id="C2right2_2" sampledSeconds="306.67" traveltime="3.64" overlapTraveltime="3.77" density="2.56" laneDensity="2.56" occupancy="1.23" waitingTime="0.00" speed="36.68" departed="0" arrived="82" entered="82" left="0" laneChangedFrom="3" laneChangedTo="4"/>
            <lane id="C2right2_3" sampledSeconds="279.62" traveltime="3.63" overlapTraveltime="3.75" density="2.33" laneDensity="2.33" occupancy="1.12" waitingTime="0.00" speed="36.85" departed="0" arrived="72" entered="76" left="0" laneChangedFrom="4" laneChangedTo="0"/>
        </edge>
        <edge id="C2top2">
            <lane id="C2top2_0" sampledSeconds="0.00" departed="0" arrived="0" entered="0" left="0" laneChangedFrom="0" laneChangedTo="0"/>
            <lane id="C2top2_1" sampledSeconds="0.00" departed="0" arrived="0" entered="0" left="0" laneChangedFrom="0" laneChangedTo="0"/>
            <lane id="C2top2_2" sampledSeconds="0.00" departed="0" arrived="0" entered="0" left="0" laneChangedFrom="0" laneChangedTo="0"/>
            <lane id="C2top2_3" sampledSeconds="0.00" departed="0" arrived="0" entered="0" left="0" laneChangedFrom="0" laneChangedTo="0"/>
        </edge>
        <edge id="bottom0A0">
            <lane id="bottom0A0_0" sampledSeconds="0.00" departed="0" arrived="0" entered="0" left="0" laneChangedFrom="0" laneChangedTo="0"/>
            <lane id="bottom0A0_1" sampledSeconds="0.00" departed="0" arrived="0" entered="0" left="0" laneChangedFrom="0" laneChangedTo="0"/>
            <lane id="bottom0A0_2" sampledSeconds="0.00" departed="0" arrived="0" entered="0" left="0" laneChangedFrom="0" laneChangedTo="0"/>
            <lane id="bottom0A0_3" sampledSeconds="0.00" departed="0" arrived="0" entered="0" left="0" laneChangedFrom="0" laneChangedTo="0"/>
        </edge>
        <edge id="bottom1B0">
            <lane id="bottom1B0_0" sampledSeconds="0.00" departed="0" arrived="0" entered="0" left="0" laneChangedFrom="0" laneChangedTo="0"/>
            <lane id="bottom1B0_1" sampledSeconds="0.00" departed="0" arrived="0" entered="0" left="0" laneChangedFrom="0" laneChangedTo="0"/>
            <lane id="bottom1B0_2" sampledSeconds="0.00" departed="0" arrived="0" entered="0" left="0" laneChangedFrom="0" laneChangedTo="0"/>
            <lane id="bottom1B0_3" sampledSeconds="0.00" departed="0" arrived="0" entered="0" left="0" laneChangedFrom="0" laneChangedTo="0"/>
        </edge>
        <edge id="bottom2C0">
            <lane id="bottom2C0_0" sampledSeconds="0.00" departed="0" arrived="0" entered="0" left="0" laneChangedFrom="0" laneChangedTo="0"/>
            <lane id="bottom2C0_1" sampledSeconds="0.00" departed="0" arrived="0" entered="0" left="0" laneChangedFrom="0" laneChangedTo="0"/>
            <lane id="bottom2C0_2" sampledSeconds="0.00" departed="0" arrived="0" entered="0" left="0" laneChangedFrom="0" laneChangedTo="0"/>
            <lane id="bottom2C0_3" sampledSeconds="0.00" departed="0" arrived="0" entered="0" left="0" laneChangedFrom="0" laneChangedTo="0"/>
        </edge>
        <edge id="left0A0">
            <lane id="left0A0_0" sampledSeconds="1880.89" traveltime="28.36" overlapTraveltime="28.97" density="15.69" laneDensity="15.69" occupancy="7.77" waitingTime="802.00" speed="4.77" departed="76" arrived="0" entered="0" left="66" laneChangedFrom="18" laneChangedTo="8"/>
            <lane id="left0A0_1" sampledSeconds="1873.69" traveltime="26.66" overlapTraveltime="27.26" density="15.63" laneDensity="15.63" occupancy="7.73" waitingTime="784.00" speed="5.07" departed="69" arrived="0" entered="0" left="70" laneChangedFrom="28" laneChangedTo="29"/>
            <lane id="left0A0_2" sampledSeconds="2011.72" traveltime="27.62" overlapTraveltime="28.20" density="16.78" laneDensity="16.78" occupancy="8.31" waitingTime="847.00" speed="4.90" departed="75" arrived="0" entered="0" left="73" laneChangedFrom="27" laneChangedTo="27"/>
            <lane id="left0A0_3" sampledSeconds="2114.33" traveltime="25.32" overlapTraveltime="25.82" density="17.64" laneDensity="17.64" occupancy="8.73" waitingTime="842.00" speed="5.35" departed="80" arrived="0" entered="0" left="88" laneChangedFrom="7" laneChangedTo="16"/>
        </edge>
        <edge id="left1A1">
            <lane id="left1A1_0" sampledSeconds="1903.14" traveltime="27.07" overlapTraveltime="27.71" density="15.88" laneDensity="15.88" occupancy="7.86" waitingTime="796.00" speed="4.99" departed="82" arrived="0" entered="0" left="65" laneChangedFrom="21" laneChangedTo="4"/>
            <lane id="left1A1_1" sampledSeconds="2092.07" traveltime="27.08" overlapTraveltime="27.65" density="17.45" laneDensity="17.45" occupancy="8.64" waitingTime="878.00" speed="5.00" departed="76" arrived="0" entered="0" left="77" laneChangedFrom="23" laneChangedTo="25"/>
            <lane id="left1A1_2" sampledSeconds="1855.39" traveltime="29.00" overlapTraveltime="29.54" density="15.48" laneDensity="15.48" occupancy="7.66" waitingTime="838.00" speed="4.68" departed="61" arrived="0" entered="0" left="71" laneChangedFrom="16" laneChangedTo="27"/>
            <lane id="left1A1_3" sampledSeconds="2075.20" traveltime="25.53" overlapTraveltime="26.06" density="17.31" laneDensity="17.31" occupancy="8.57" waitingTime="806.00" speed="5.30" departed="81" arrived="0" entered="0" left="83" laneChangedFrom="8" laneChangedTo="12"/>
        </edge>
        <edge id="left2A2">
            <lane id="left2A2_0" sampledSeconds="1924.69" traveltime="27.07" overlapTraveltime="27.65" density="16.06" laneDensity="16.06" occupancy="7.95" waitingTime="820.00" speed="5.00" departed="81" arrived="0" entered="0" left="69" laneChangedFrom="18" laneChangedTo="6"/>
            <lane id="left2A2_1" sampledSeconds="1935.60" traveltime="29.28" overlapTraveltime="29.92" density="16.15" laneDensity="16.15" occupancy="7.99" waitingTime="879.00" speed="4.62" departed="67" arrived="0" entered="0" left="64" laneChangedFrom="25" laneChangedTo="23"/>
            <lane id="left2A2_2" sampledSeconds="2016.92" traveltime="24.18" overlapTraveltime="24.73" density="16.82" laneDensity="16.82" occupancy="8.32" waitingTime="734.00" speed="5.59" departed="81" arrived="0" entered="0" left="83" laneChangedFrom="21" laneChangedTo="25"/>
            <lane id="left2A2_3" sampledSeconds="1888.95" traveltime="26.16" overlapTraveltime="26.68" density="15.76" laneDensity="15.76" occupancy="7.79" waitingTime="768.00" speed="5.18" departed="71" arrived="0" entered="0" left="80" laneChangedFrom="6" laneChangedTo="16"/>
        </edge>
        <edge id="right0C0">
            <lane id="right0C0_0" sampledSeconds="0.00" departed="0" arrived="0" entered="0" left="0" laneChangedFrom="0" laneChangedTo="0"/>
            <lane id="right0C0_1" sampledSeconds="0.00" departed="0" arrived="0" entered="0" left="0" laneChangedFrom="0" laneChangedTo="0"/>
            <lane id="right0C0_2" sampledSeconds="0.00" departed="0" arrived="0" entered="0" left="0" laneChangedFrom="0" laneChangedTo="0"/>
            <lane id="right0C0_3" sampledSeconds="0.00" departed="0" arrived="0" entered="0" left="0" laneChangedFrom="0" laneChangedTo="0"/>
        </edge>
        <edge id="right1C1">
            <lane id="right1C1_0" sampledSeconds="0.00" departed="0" arrived="0" entered="0" left="0" laneChangedFrom="0" laneChangedTo="0"/>
            <lane id="right1C1_1" sampledSeconds="0.00" departed="0" arrived="0" entered="0" left="0" laneChangedFrom="0" laneChangedTo="0"/>
            <lane id="right1C1_2" sampledSeconds="0.00" departed="0" arrived="0" entered="0" left="0" laneChangedFrom="0" laneChangedTo="0"/>
            <lane id="right1C1_3" sampledSeconds="0.00" departed="0" arrived="0" entered="0" left="0" laneChangedFrom="0" laneChangedTo="0"/>
        </edge>
        <edge id="right2C2">
            <lane id="right2C2_0" sampledSeconds="0.00" departed="0" arrived="0" entered="0" left="0" laneChangedFrom="0" laneChangedTo="0"/>
            <lane id="right2C2_1" sampledSeconds="0.00" departed="0" arrived="0" entered="0" left="0" laneChangedFrom="0" laneChangedTo="0"/>
            <lane id="right2C2_2" sampledSeconds="0.00" departed="0" arrived="0" entered="0" left="0" laneChangedFrom="0" laneChangedTo="0"/>
            <lane id="right2C2_3" sampledSeconds="0.00" departed="0" arrived="0" entered="0" left="0" laneChangedFrom="0" laneChangedTo="0"/>
        </edge>
        <edge id="top0A2">
            <lane id="top0A2_0" sampledSeconds="2060.78" traveltime="27.20" overlapTraveltime="27.79" density="17.19" laneDensity="17.19" occupancy="8.52" waitingTime="904.00" speed="4.97" departed="87" arrived="0" entered="0" left="69" laneChangedFrom="17" laneChangedTo="3"/>
            <lane id="top0A2_1" sampledSeconds="1823.75" traveltime="27.36" overlapTraveltime="27.97" density="15.21" laneDensity="15.21" occupancy="7.53" waitingTime="811.00" speed="4.94" departed="65" arrived="0" entered="0" left="64" laneChangedFrom="17" laneChangedTo="20"/>
            <lane id="top0A2_2" sampledSeconds="1855.44" traveltime="26.87" overlapTraveltime="27.41" density="15.48" laneDensity="15.48" occupancy="7.66" waitingTime="758.00" speed="5.04" departed="69" arrived="0" entered="0" left="71" laneChangedFrom="15" laneChangedTo="22"/>
            <lane id="top0A2_3" sampledSeconds="2117.68" traveltime="26.70" overlapTraveltime="27.26" density="17.67" laneDensity="17.67" occupancy="8.75" waitingTime="887.00" speed="5.07" departed="79" arrived="0" entered="0" left="77" laneChangedFrom="8" laneChangedTo="12"/>
        </edge>
        <edge id="top1B2">
            <lane id="top1B2_0" sampledSeconds="956.28" traveltime="21.79" overlapTraveltime="22.63" density="7.98" laneDensity="7.98" occupancy="3.95" waitingTime="212.00" speed="6.11" departed="81" arrived="0" entered="0" left="24" laneChangedFrom="63" laneChangedTo="9"/>
            <lane id="top1B2_1" sampledSeconds="3484.53" traveltime="37.10" overlapTraveltime="37.70" density="29.07" laneDensity="29.07" occupancy="14.41" waitingTime="1762.00" speed="3.67" departed="77" arrived="0" entered="0" left="96" laneChangedFrom="52" laneChangedTo="77"/>
            <lane id="top1B2_2" sampledSeconds="3610.69" traveltime="34.55" overlapTraveltime="35.40" density="30.12" laneDensity="30.12" occupancy="14.88" waitingTime="1656.00" speed="3.90" departed="71" arrived="0" entered="0" left="103" laneChangedFrom="83" laneChangedTo="121"/>
            <lane id="top1B2_3" sampledSeconds="2042.61" traveltime="42.15" overlapTraveltime="42.69" density="17.04" laneDensity="17.04" occupancy="8.44" waitingTime="990.00" speed="3.24" departed="71" arrived="0" entered="0" left="58" laneChangedFrom="78" laneChangedTo="69"/>
        </edge>
        <edge id="top2C2">
            <lane id="top2C2_0" sampledSeconds="1917.87" traveltime="30.38" overlapTraveltime="31.11" density="16.00" laneDensity="16.00" occupancy="7.93" waitingTime="891.00" speed="4.44" departed="73" arrived="0" entered="0" left="55" laneChangedFrom="19" laneChangedTo="4"/>
            <lane id="top2C2_1" sampledSeconds="2076.88" traveltime="26.92" overlapTraveltime="27.46" density="17.32" laneDensity="17.32" occupancy="8.58" waitingTime="909.00" speed="5.03" departed="79" arrived="0" entered="0" left="76" laneChangedFrom="21" laneChangedTo="21"/>
            <lane id="top2C2_2" sampledSeconds="1980.00" traveltime="27.22" overlapTraveltime="27.80" density="16.52" laneDensity="16.52" occupancy="8.18" waitingTime="832.00" speed="4.97" departed="76" arrived="0" entered="0" left="71" laneChangedFrom="20" laneChangedTo="21"/>
            <lane id="top2C2_3" sampledSeconds="1886.10" traveltime="24.25" overlapTraveltime="24.77" density="15.73" laneDensity="15.73" occupancy="7.78" waitingTime="730.00" speed="5.58" departed="72" arrived="0" entered="0" left="79" laneChangedFrom="4" laneChangedTo="18"/>
        </edge>
    </interval>
    <interval begin="900.00" end="1800.00" id="15min-lane">
        <edge id="A0A1">
            <lane id="A0A1_0" sampledSeconds="0.00" departed="0" arrived="0" entered="0" left="0" laneChangedFrom="0" laneChangedTo="0"/>
            <lane id="A0A1_1" sampledSeconds="0.00" departed="0" arrived="0" entered="0" left="0" laneChangedFrom="0" laneChangedTo="0"/>
            <lane id="A0A1_2" sampledSeconds="0.00" departed="0" arrived="0" entered="0" left="0" laneChangedFrom="0" laneChangedTo="0"/>
            <lane id="A0A1_3" sampledSeconds="0.00" departed="0" arrived="0" entered="0" left="0" laneChangedFrom="0" laneChangedTo="0"/>
        </edge>
        <edge id="A0B0">
            <lane id="A0B0_0" sampledSeconds="629.83" traveltime="8.68" overlapTraveltime="9.01" density="6.01" laneDensity="6.01" occupancy="2.90" waitingTime="189.00" speed="13.47" departed="0" arrived="0" entered="69" left="74" laneChangedFrom="1" laneChangedTo="6"/>
            <lane id="A0B0_1" sampledSeconds="558.36" traveltime="8.24" overlapTraveltime="8.50" density="5.33" laneDensity="5.33" occupancy="2.57" waitingTime="150.00" speed="14.28" departed="0" arrived="0" entered="66" left="65" laneChangedFrom="7" laneChangedTo="6"/>
            <lane id="A0B0_2" sampledSeconds="615.38" traveltime="7.51" overlapTraveltime="7.74" density="5.87" laneDensity="5.87" occupancy="2.84" waitingTime="134.00" speed="15.69" departed="0" arrived="0" entered="79" left="79" laneChangedFrom="6" laneChangedTo="6"/>
            <lane id="A0B0_3" sampledSeconds="680.63" traveltime="7.78" overlapTraveltime="8.03" density="6.50" laneDensity="6.50" occupancy="3.14" waitingTime="184.00" speed="15.12" departed="0" arrived="0" entered="86" left="81" laneChangedFrom="5" laneChangedTo="1"/>
        </edge>
        <edge id="A0bottom0">
            <lane id="A0bottom0_0" sampledSeconds="383.20" traveltime="5.79" overlapTraveltime="5.97" density="3.20" laneDensity="3.20" occupancy="1.54" waitingTime="0.00" speed="23.17" departed="0" arrived="66" entered="64" left="0" laneChangedFrom="0" laneChangedTo="2"/>
            <lane id="A0bottom0_1" sampledSeconds="446.71" traveltime="5.92" overlapTraveltime="6.10" density="3.73" laneDensity="3.73" occupancy="1.80" waitingTime="0.00" speed="22.64" departed="0" arrived="72" entered="74" left="0" laneChangedFrom="2" laneChangedTo="0"/>
            <lane id="A0bottom0_2" sampledSeconds="441.81" traveltime="5.65" overlapTraveltime="5.82" density="3.69" laneDensity="3.69" occupancy="1.78" waitingTime="0.00" speed="23.73" departed="0" arrived="77" entered="76" left="0" laneChangedFrom="0" laneChangedTo="1"/>
            <lane id="A0bottom0_3" sampledSeconds="442.80" traveltime="5.02" overlapTraveltime="5.17" density="3.69" laneDensity="3.69" occupancy="1.78" waitingTime="0.00" speed="26.71" departed="0" arrived="85" entered="86" left="0" laneChangedFrom="1" laneChangedTo="0"/>
        </edge>
        <edge id="A0left0">
            <lane id="A0left0_0" sampledSeconds="0.00" departed="0" arrived="0" entered="0" left="0" laneChangedFrom="0" laneChangedTo="0"/>
            <lane id="A0left0_1" sampledSeconds="0.00" departed="0" arrived="0" entered="0" left="0" laneChangedFrom="0" laneChangedTo="0"/>
            <lane id="A0left0_2" sampledSeconds="0.00" departed="0" arrived="0" entered="0" left="0" laneChangedFrom="0" laneChangedTo="0"/>
            <lane id="A0left0_3" sampledSeconds="0.00" departed="0" arrived="0" entered="0" left="0" laneChangedFrom="0" laneChangedTo="0"/>
        </edge>
        <edge id="A1A0">
            <lane id="A1A0_0" sampledSeconds="415.82" traveltime="6.23" overlapTraveltime="6.60" density="3.97" laneDensity="3.97" occupancy="1.90" waitingTime="0.00" speed="18.39" departed="0" arrived="0" entered="63" left="63" laneChangedFrom="0" laneChangedTo="0"/>
            <lane id="A1A0_1" sampledSeconds="524.00" traveltime="6.63" overlapTraveltime="6.99" density="5.00" laneDensity="5.00" occupancy="2.40" waitingTime="0.00" speed="17.38" departed="0" arrived="0" entered="75" left="75" laneChangedFrom="0" laneChangedTo="0"/>
            <lane id="A1A0_2" sampledSeconds="546.32" traveltime="6.68" overlapTraveltime="7.05" density="5.21" laneDensity="5.21" occupancy="2.50" waitingTime="0.00" speed="17.22" departed="0" arrived="0" entered="78" left="76" laneChangedFrom="3" laneChangedTo="1"/>
            <lane id="A1A0_3" sampledSeconds="515.49" traveltime="5.79" overlapTraveltime="6.10" density="4.92" laneDensity="4.92" occupancy="2.36" waitingTime="0.00" speed="19.90" departed="0" arrived="0" entered="84" left="86" laneChangedFrom="1" laneChangedTo="3"/>
        </edge>
        <edge id="A1A2">
            <lane id="A1A2_0" sampledSeconds="0.00" departed="0" arrived="0" entered="0" left="0" laneChangedFrom="0" laneChangedTo="0"/>
            <lane id="A1A2_1" sampledSeconds="0.00" departed="0" arrived="0" entered="0" left="0" laneChangedFrom="0" laneChangedTo="0"/>
            <lane id="A1A2_2" sampledSeconds="0.00" departed="0" arrived="0" entered="0" left="0" laneChangedFrom="0" laneChangedTo="0"/>
            <lane id="A1A2_3" sampledSeconds="0.00" departed="0" arrived="0" entered="0" left="0" laneChangedFrom="0" laneChangedTo="0"/>
        </edge>
        <edge id="A1B1">
            <lane id="A1B1_0" sampledSeconds="639.67" traveltime="9.20" overlapTraveltime="9.54" density="6.11" laneDensity="6.11" occupancy="2.94" waitingTime="220.00" speed="12.73" departed="0" arrived="0" entered="69" left="73" laneChangedFrom="2" laneChangedTo="6"/>
            <lane id="A1B1_1" sampledSeconds="558.03" traveltime="6.80" overlapTraveltime="7.01" density="5.33" laneDensity="5.33" occupancy="2.57" waitingTime="83.00" speed="17.31" departed="0" arrived="0" entered="78" left="77" laneChangedFrom="6" laneChangedTo="5"/>
            <lane id="A1B1_2" sampledSeconds="507.50" traveltime="6.02" overlapTraveltime="6.22" density="4.84" laneDensity="4.84" occupancy="2.32" waitingTime="38.00" speed="19.50" departed="0" arrived="0" entered="81" left="81" laneChangedFrom="3" laneChangedTo="2"/>
            <lane id="A1B1_3" sampledSeconds="465.67" traveltime="6.29" overlapTraveltime="6.48" density="4.45" laneDensity="4.45" occupancy="2.14" waitingTime="51.00" speed="18.74" departed="0" arrived="0" entered="72" left="70" laneChangedFrom="2" laneChangedTo="0"/>
        </edge>
        <edge id="A1left1">
            <lane id="A1left1_0" sampledSeconds="0.00" departed="0" arrived="0" entered="0" left="0" laneChangedFrom="0" laneChangedTo="0"/>
            <lane id="A1left1_1" sampledSeconds="0.00" departed="0" arrived="0" entered="0" left="0" laneChangedFrom="0" laneChangedTo="0"/>
            <lane id="A1left1_2" sampledSeconds="0.00" departed="0" arrived="0" entered="0" left="0" laneChangedFrom="0" laneChangedTo="0"/>
            <lane id="A1left1_3" sampledSeconds="0.00" departed="0" arrived="0" entered="0" left="0" laneChangedFrom="0" laneChangedTo="0"/>
        </edge>
        <edge id="A2A1">
            <lane id="A2A1_0" sampledSeconds="361.34" traveltime="5.58" overlapTraveltime="5.78" density="3.45" laneDensity="3.45" occupancy="1.65" waitingTime="0.00" speed="21.01" departed="0" arrived="0" entered="64" left="61" laneChangedFrom="3" laneChangedTo="0"/>
            <lane id="A2A1_1" sampledSeconds="432.26" traveltime="5.75" overlapTraveltime="5.95" density="4.13" laneDensity="4.13" occupancy="1.97" waitingTime="0.00" speed="20.39" departed="0" arrived="0" entered="70" left="76" laneChangedFrom="0" laneChangedTo="6"/>
            <lane id="A2A1_2" sampledSeconds="459.36" traveltime="5.65" overlapTraveltime="5.85" density="4.38" laneDensity="4.38" occupancy="2.10" waitingTime="0.00" speed="20.75" departed="0" arrived="0" entered="79" left="77" laneChangedFrom="3" laneChangedTo="1"/>
            <lane id="A2A1_3" sampledSeconds="470.73" traveltime="5.27" overlapTraveltime="5.45" density="4.49" laneDensity="4.49" occupancy="2.15" waitingTime="0.00" speed="22.26" departed="0" arrived="0" entered="87" left="86" laneChangedFrom="1" laneChangedTo="0"/>
        </edge>
        <edge id="A2B2">
            <lane id="A2B2_0" sampledSeconds="397.61" traveltime="5.62" overlapTraveltime="5.82" density="3.80" laneDensity="3.80" occupancy="1.81" waitingTime="0.00" speed="20.86" departed="0" arrived="0" entered="69" left="68" laneChangedFrom="0" laneChangedTo="0"/>
            <lane id="A2B2_1" sampledSeconds="433.69" traveltime="5.52" overlapTraveltime="5.72" density="4.14" laneDensity="4.14" occupancy="1.98" waitingTime="0.00" speed="21.22" departed="0" arrived="0" entered="76" left="76" laneChangedFrom="1" laneChangedTo="1"/>
            <lane id="A2B2_2" sampledSeconds="441.66" traveltime="5.48" overlapTraveltime="5.67" density="4.22" laneDensity="4.22" occupancy="2.01" waitingTime="0.00" speed="21.39" departed="0" arrived="0" entered="77" left="79" laneChangedFrom="1" laneChangedTo="2"/>
            <lane id="A2B2_3" sampledSeconds="427.01" traveltime="5.30" overlapTraveltime="5.48" density="4.08" laneDensity="4.08" occupancy="1.95" waitingTime="0.00" speed="22.15" departed="0" arrived="0" entered="78" left="77" laneChangedFrom="1" laneChangedTo="0"/>
        </edge>
        <edge id="A2left2">
            <lane id="A2left2_0" sampledSeconds="0.00" departed="0" arrived="0" entered="0" left="0" laneChangedFrom="0" laneChangedTo="0"/>
            <lane id="A2left2_1" sampledSeconds="0.00" departed="0" arrived="0" entered="0" left="0" laneChangedFrom="0" laneChangedTo="0"/>
            <lane id="A2left2_2" sampledSeconds="0.00" departed="0" arrived="0" entered="0" left="0" laneChangedFrom="0" laneChangedTo="0"/>
            <lane id="A2left2_3" sampledSeconds="0.00" departed="0" arrived="0" entered="0" left="0" laneChangedFrom="0" laneChangedTo="0"/>
        </edge>
        <edge id="A2top0">
            <lane id="A2top0_0" sampledSeconds="0.00" departed="0" arrived="0" entered="0" left="0" laneChangedFrom="0" laneChangedTo="0"/>
            <lane id="A2top0_1" sampledSeconds="0.00" departed="0" arrived="0" entered="0" left="0" laneChangedFrom="0" laneChangedTo="0"/>
            <lane id="A2top0_2" sampledSeconds="0.00" departed="0" arrived="0" entered="0" left="0" laneChangedFrom="0" laneChangedTo="0"/>
            <lane id="A2top0_3" sampledSeconds="0.00" departed="0" arrived="0" entered="0" left="0" laneChangedFrom="0" laneChangedTo="0"/>
        </edge>
        <edge id="B0A0">
            <lane id="B0A0_0" sampledSeconds="0.00" departed="0" arrived="0" entered="0" left="0" laneChangedFrom="0" laneChangedTo="0"/>
            <lane id="B0A0_1" sampledSeconds="0.00" departed="0" arrived="0" entered="0" left="0" laneChangedFrom="0" laneChangedTo="0"/>
            <lane id="B0A0_2" sampledSeconds="0.00" departed="0" arrived="0" entered="0" left="0" laneChangedFrom="0" laneChangedTo="0"/>
            <lane id="B0A0_3" sampledSeconds="0.00" departed="0" arrived="0" entered="0" left="0" laneChangedFrom="0" laneChangedTo="0"/>
        </edge>
        <edge id="B0B1">
            <lane id="B0B1_0" sampledSeconds="0.00" departed="0" arrived="0" entered="0" left="0" laneChangedFrom="0" laneChangedTo="0"/>
            <lane id="B0B1_1" sampledSeconds="0.00" departed="0" arrived="0" entered="0" left="0" laneChangedFrom="0" laneChangedTo="0"/>
            <lane id="B0B1_2" sampledSeconds="0.00" departed="0" arrived="0" entered="0" left="0" laneChangedFrom="0" laneChangedTo="0"/>
            <lane id="B0B1_3" sampledSeconds="0.00" departed="0" arrived="0" entered="0" left="0" laneChangedFrom="0" laneChangedTo="0"/>
        </edge>
        <edge id="B0C0">
            <lane id="B0C0_0" sampledSeconds="499.29" traveltime="6.57" overlapTraveltime="6.80" density="4.77" laneDensity="4.77" occupancy="2.31" waitingTime="154.00" speed="17.86" departed="0" arrived="0" entered="74" left="73" laneChangedFrom="1" laneChangedTo="1"/>
            <lane id="B0C0_1" sampledSeconds="400.91" traveltime="6.03" overlapTraveltime="6.24" density="3.83" laneDensity="3.83" occupancy="1.85" waitingTime="111.00" speed="19.44" departed="0" arrived="0" entered="65" left="63" laneChangedFrom="1" laneChangedTo="1"/>
            <lane id="B0C0_2" sampledSeconds="456.24" traveltime="5.44" overlapTraveltime="5.63" density="4.36" laneDensity="4.36" occupancy="2.11" waitingTime="114.00" speed="21.55" departed="0" arrived="0" entered="80" left="82" laneChangedFrom="0" laneChangedTo="2"/>
            <lane id="B0C0_3" sampledSeconds="354.96" traveltime="4.25" overlapTraveltime="4.41" density="3.39" laneDensity="3.39" occupancy="1.63" waitingTime="39.00" speed="27.52" departed="0" arrived="0" entered="81" left="80" laneChangedFrom="2" laneChangedTo="0"/>
        </edge>
        <edge id="B0bottom1">
            <lane id="B0bottom1_0" sampledSeconds="524.30" traveltime="3.65" overlapTraveltime="3.78" density="4.37" laneDensity="4.37" occupancy="2.11" waitingTime="0.00" speed="36.56" departed="0" arrived="139" entered="139" left="0" laneChangedFrom="0" laneChangedTo="0"/>
            <lane id="B0bottom1_1" sampledSeconds="596.01" traveltime="3.59" overlapTraveltime="3.71" density="4.97" laneDensity="4.97" occupancy="2.40" waitingTime="0.00" speed="37.26" departed="0" arrived="161" entered="161" left="0" laneChangedFrom="0" laneChangedTo="0"/>
        </edge>
        <edge id="B1A1">
            <lane id="B1A1_0" sampledSeconds="0.00" departed="0" arrived="0" entered="0" left="0" laneChangedFrom="0" laneChangedTo="0"/>
            <lane id="B1A1_1" sampledSeconds="0.00" departed="0" arrived="0" entered="0" left="0" laneChangedFrom="0" laneChangedTo="0"/>
            <lane id="B1A1_2" sampledSeconds="0.00" departed="0" arrived="0" entered="0" left="0" laneChangedFrom="0" laneChangedTo="0"/>
            <lane id="B1A1_3" sampledSeconds="0.00" departed="0" arrived="0" entered="0" left="0" laneChangedFrom="0" laneChangedTo="0"/>
        </edge>
        <edge id="B1B0">
            <lane id="B1B0_0" sampledSeconds="0.00" departed="0" arrived="0" entered="0" left="0" laneChangedFrom="0" laneChangedTo="0"/>
            <lane id="B1B0_1" sampledSeconds="611.72" traveltime="4.30" overlapTraveltime="4.46" density="5.84" laneDensity="5.84" occupancy="2.80" waitingTime="0.00" speed="27.20" departed="0" arrived="0" entered="137" left="138" laneChangedFrom="0" laneChangedTo="1"/>
            <lane id="B1B0_2" sampledSeconds="702.76" traveltime="4.16" overlapTraveltime="4.31" density="6.71" laneDensity="6.71" occupancy="3.21" waitingTime="0.00" speed="28.15" departed="0" arrived="0" entered="163" left="162" laneChangedFrom="1" laneChangedTo="0"/>
            <lane id="B1B0_3" sampledSeconds="0.00" departed="0" arrived="0" entered="0" left="0" laneChangedFrom="0" laneChangedTo="0"/>
        </edge>
        <edge id="B1B2">
            <lane id="B1B2_0" sampledSeconds="0.00" departed="0" arrived="0" entered="0" left="0" laneChangedFrom="0" laneChangedTo="0"/>
            <lane id="B1B2_1" sampledSeconds="0.00" departed="0" arrived="0" entered="0" left="0" laneChangedFrom="0" laneChangedTo="0"/>
            <lane id="B1B2_2" sampledSeconds="0.00" departed="0" arrived="0" entered="0" left="0" laneChangedFrom="0" laneChangedTo="0"/>
            <lane id="B1B2_3" sampledSeconds="0.00" departed="0" arrived="0" entered="0" left="0" laneChangedFrom="0" laneChangedTo="0"/>
        </edge>
        <edge id="B1C1">
            <lane id="B1C1_0" sampledSeconds="502.11" traveltime="6.50" overlapTraveltime="6.72" density="4.79" laneDensity="4.79" occupancy="2.32" waitingTime="152.00" speed="18.05" departed="0" arrived="0" entered="73" left="75" laneChangedFrom="0" laneChangedTo="2"/>
            <lane id="B1C1_1" sampledSeconds="343.89" traveltime="4.38" overlapTraveltime="4.55" density="3.28" laneDensity="3.28" occupancy="1.58" waitingTime="37.00" speed="26.71" departed="0" arrived="0" entered="77" left="77" laneChangedFrom="2" laneChangedTo="2"/>
            <lane id="B1C1_2" sampledSeconds="446.71" traveltime="5.28" overlapTraveltime="5.47" density="4.26" laneDensity="4.26" occupancy="2.06" waitingTime="111.00" speed="22.20" departed="0" arrived="0" entered="81" left="82" laneChangedFrom="2" laneChangedTo="2"/>
            <lane id="B1C1_3" sampledSeconds="345.89" traveltime="4.87" overlapTraveltime="5.05" density="3.30" laneDensity="3.30" occupancy="1.59" waitingTime="75.00" speed="24.03" departed="0" arrived="0" entered="70" left="67" laneChangedFrom="2" laneChangedTo="0"/>
        </edge>
        <edge id="B2A2">
            <lane id="B2A2_0" sampledSeconds="0.00" departed="0" arrived="0" entered="0" left="0" laneChangedFrom="0" laneChangedTo="0"/>
            <lane id="B2A2_1" sampledSeconds="0.00" departed="0" arrived="0" entered="0" left="0" laneChangedFrom="0" laneChangedTo="0"/>
            <lane id="B2A2_2" sampledSeconds="0.00" departed="0" arrived="0" entered="0" left="0" laneChangedFrom="0" laneChangedTo="0"/>
            <lane id="B2A2_3" sampledSeconds="0.00" departed="0" arrived="0" entered="0" left="0" laneChangedFrom="0" laneChangedTo="0"/>
        </edge>
        <edge id="B2B1">
            <lane id="B2B1_0" sampledSeconds="85.94" traveltime="8.51" overlapTraveltime="8.87" density="0.82" laneDensity="0.82" occupancy="0.38" waitingTime="0.00" speed="13.69" departed="0" arrived="0" entered="29" left="0" laneChangedFrom="29" laneChangedTo="0"/>
            <lane id="B2B1_1" sampledSeconds="1004.40" traveltime="7.64" overlapTraveltime="7.87" density="9.59" laneDensity="9.59" occupancy="4.59" waitingTime="0.00" speed="15.42" departed="0" arrived="0" entered="109" left="137" laneChangedFrom="6" laneChangedTo="34"/>
            <lane id="B2B1_2" sampledSeconds="1218.17" traveltime="7.97" overlapTraveltime="8.19" density="11.63" laneDensity="11.63" occupancy="5.56" waitingTime="0.00" speed="14.82" departed="0" arrived="0" entered="114" left="161" laneChangedFrom="5" laneChangedTo="52"/>
            <lane id="B2B1_3" sampledSeconds="124.42" traveltime="8.55" overlapTraveltime="8.91" density="1.19" laneDensity="1.19" occupancy="0.54" waitingTime="0.00" speed="13.63" departed="0" arrived="0" entered="48" left="2" laneChangedFrom="46" laneChangedTo="0"/>
        </edge>
        <edge id="B2C2">
            <lane id="B2C2_0" sampledSeconds="457.63" traveltime="6.24" overlapTraveltime="6.46" density="4.37" laneDensity="4.37" occupancy="2.12" waitingTime="151.00" speed="18.79" departed="0" arrived="0" entered="68" left="73" laneChangedFrom="1" laneChangedTo="5"/>
            <lane id="B2C2_1" sampledSeconds="680.73" traveltime="8.94" overlapTraveltime="9.26" density="6.50" laneDensity="6.50" occupancy="3.17" waitingTime="323.00" speed="13.11" departed="0" arrived="0" entered="76" left="72" laneChangedFrom="6" laneChangedTo="2"/>
            <lane id="B2C2_2" sampledSeconds="731.40" traveltime="8.84" overlapTraveltime="9.14" density="6.98" laneDensity="6.98" occupancy="3.40" waitingTime="353.00" speed="13.29" departed="0" arrived="0" entered="81" left="80" laneChangedFrom="2" laneChangedTo="2"/>
            <lane id="B2C2_3" sampledSeconds="532.72" traveltime="6.80" overlapTraveltime="7.04" density="5.09" laneDensity="5.09" occupancy="2.47" waitingTime="212.00" speed="17.23" departed="0" arrived="0" entered="76" left="75" laneChangedFrom="1" laneChangedTo="1"/>
        </edge>
        <edge id="B2top1">
            <lane id="B2top1_0" sampledSeconds="0.00" departed="0" arrived="0" entered="0" left="0" laneChangedFrom="0" laneChangedTo="0"/>
            <lane id="B2top1_1" sampledSeconds="0.00" departed="0" arrived="0" entered="0" left="0" laneChangedFrom="0" laneChangedTo="0"/>
            <lane id="B2top1_2" sampledSeconds="0.00" departed="0" arrived="0" entered="0" left="0" laneChangedFrom="0" laneChangedTo="0"/>
            <lane id="B2top1_3" sampledSeconds="0.00" departed="0" arrived="0" entered="0" left="0" laneChangedFrom="0" laneChangedTo="0"/>
        </edge>
        <edge id="C0B0">
            <lane id="C0B0_0" sampledSeconds="0.00" departed="0" arrived="0" entered="0" left="0" laneChangedFrom="0" laneChangedTo="0"/>
            <lane id="C0B0_1" sampledSeconds="0.00" departed="0" arrived="0" entered="0" left="0" laneChangedFrom="0" laneChangedTo="0"/>
            <lane id="C0B0_2" sampledSeconds="0.00" departed="0" arrived="0" entered="0" left="0" laneChangedFrom="0" laneChangedTo="0"/>
            <lane id="C0B0_3" sampledSeconds="0.00" departed="0" arrived="0" entered="0" left="0" laneChangedFrom="0" laneChangedTo="0"/>
        </edge>
        <edge id="C0C1">
            <lane id="C0C1_0" sampledSeconds="0.00" departed="0" arrived="0" entered="0" left="0" laneChangedFrom="0" laneChangedTo="0"/>
            <lane id="C0C1_1" sampledSeconds="0.00" departed="0" arrived="0" entered="0" left="0" laneChangedFrom="0" laneChangedTo="0"/>
            <lane id="C0C1_2" sampledSeconds="0.00" departed="0" arrived="0" entered="0" left="0" laneChangedFrom="0" laneChangedTo="0"/>
            <lane id="C0C1_3" sampledSeconds="0.00" departed="0" arrived="0" entered="0" left="0" laneChangedFrom="0" laneChangedTo="0"/>
        </edge>
        <edge id="C0bottom2">
            <lane id="C0bottom2_0" sampledSeconds="386.97" traveltime="6.09" overlapTraveltime="6.27" density="3.23" laneDensity="3.23" occupancy="1.56" waitingTime="0.00" speed="22.03" departed="0" arrived="63" entered="61" left="0" laneChangedFrom="0" laneChangedTo="2"/>
            <lane id="C0bottom2_1" sampledSeconds="463.32" traveltime="5.74" overlapTraveltime="5.92" density="3.86" laneDensity="3.86" occupancy="1.86" waitingTime="0.00" speed="23.34" departed="0" arrived="78" entered="79" left="0" laneChangedFrom="2" laneChangedTo="1"/>
            <lane id="C0bottom2_2" sampledSeconds="485.85" traveltime="5.75" overlapTraveltime="5.92" density="4.05" laneDensity="4.05" occupancy="1.95" waitingTime="0.00" speed="23.33" departed="0" arrived="84" entered="82" left="0" laneChangedFrom="1" laneChangedTo="3"/>
            <lane id="C0bottom2_3" sampledSeconds="447.69" traveltime="5.63" overlapTraveltime="5.81" density="3.73" laneDensity="3.73" occupancy="1.80" waitingTime="0.00" speed="23.80" departed="0" arrived="75" entered="78" left="0" laneChangedFrom="3" laneChangedTo="0"/>
        </edge>
        <edge id="C0right0">
            <lane id="C0right0_0" sampledSeconds="282.38" traveltime="3.76" overlapTraveltime="3.88" density="2.36" laneDensity="2.36" occupancy="1.13" waitingTime="0.00" speed="35.59" departed="0" arrived="73" entered="73" left="0" laneChangedFrom="0" laneChangedTo="0"/>
            <lane id="C0right0_1" sampledSeconds="250.08" traveltime="3.73" overlapTraveltime="3.86" density="2.09" laneDensity="2.09" occupancy="1.01" waitingTime="0.00" speed="35.80" departed="0" arrived="67" entered="64" left="0" laneChangedFrom="0" laneChangedTo="2"/>
            <lane id="C0right0_2" sampledSeconds="295.51" traveltime="3.56" overlapTraveltime="3.68" density="2.47" laneDensity="2.47" occupancy="1.19" waitingTime="0.00" speed="37.57" departed="0" arrived="81" entered="81" left="0" laneChangedFrom="2" laneChangedTo="2"/>
            <lane id="C0right0_3" sampledSeconds="280.24" traveltime="3.37" overlapTraveltime="3.49" density="2.34" laneDensity="2.34" occupancy="1.13" waitingTime="0.00" speed="39.59" departed="0" arrived="79" entered="81" left="0" laneChangedFrom="2" laneChangedTo="0"/>
        </edge>
        <edge id="C1B1">
            <lane id="C1B1_0" sampledSeconds="0.00" departed="0" arrived="0" entered="0" left="0" laneChangedFrom="0" laneChangedTo="0"/>
            <lane id="C1B1_1" sampledSeconds="0.00" departed="0" arrived="0" entered="0" left="0" laneChangedFrom="0" laneChangedTo="0"/>
            <lane id="C1B1_2" sampledSeconds="0.00" departed="0" arrived="0" entered="0" left="0" laneChangedFrom="0" laneChangedTo="0"/>
            <lane id="C1B1_3" sampledSeconds="0.00" departed="0" arrived="0" entered="0" left="0" laneChangedFrom="0" laneChangedTo="0"/>
        </edge>
        <edge id="C1C0">
            <lane id="C1C0_0" sampledSeconds="421.00" traveltime="6.59" overlapTraveltime="6.98" density="4.02" laneDensity="4.02" occupancy="1.93" waitingTime="0.00" speed="17.39" departed="0" arrived="0" entered="60" left="61" laneChangedFrom="0" laneChangedTo="1"/>
            <lane id="C1C0_1" sampledSeconds="544.12" traveltime="6.40" overlapTraveltime="6.78" density="5.19" laneDensity="5.19" occupancy="2.49" waitingTime="0.00" speed="17.91" departed="0" arrived="0" entered="81" left="79" laneChangedFrom="2" laneChangedTo="0"/>
            <lane id="C1C0_2" sampledSeconds="560.17" traveltime="6.47" overlapTraveltime="6.84" density="5.35" laneDensity="5.35" occupancy="2.56" waitingTime="0.00" speed="17.74" departed="0" arrived="0" entered="82" left="82" laneChangedFrom="1" laneChangedTo="1"/>
            <lane id="C1C0_3" sampledSeconds="536.82" traveltime="6.55" overlapTraveltime="6.93" density="5.12" laneDensity="5.12" occupancy="2.46" waitingTime="0.00" speed="17.53" departed="0" arrived="0" entered="77" left="78" laneChangedFrom="0" laneChangedTo="1"/>
        </edge>
        <edge id="C1C2">
            <lane id="C1C2_0" sampledSeconds="0.00" departed="0" arrived="0" entered="0" left="0" laneChangedFrom="0" laneChangedTo="0"/>
            <lane id="C1C2_1" sampledSeconds="0.00" departed="0" arrived="0" entered="0" left="0" laneChangedFrom="0" laneChangedTo="0"/>
            <lane id="C1C2_2" sampledSeconds="0.00" departed="0" arrived="0" entered="0" left="0" laneChangedFrom="0" laneChangedTo="0"/>
            <lane id="C1C2_3" sampledSeconds="0.00" departed="0" arrived="0" entered="0" left="0" laneChangedFrom="0" laneChangedTo="0"/>
        </edge>
        <edge id="C1right1">
            <lane id="C1right1_0" sampledSeconds="304.88" traveltime="3.87" overlapTraveltime="4.00" density="2.54" laneDensity="2.54" occupancy="1.23" waitingTime="0.00" speed="34.58" departed="0" arrived="77" entered="76" left="0" laneChangedFrom="0" laneChangedTo="1"/>
            <lane id="C1right1_1" sampledSeconds="279.88" traveltime="3.54" overlapTraveltime="3.66" density="2.33" laneDensity="2.33" occupancy="1.13" waitingTime="0.00" speed="37.73" departed="0" arrived="77" entered="75" left="0" laneChangedFrom="1" laneChangedTo="3"/>
            <lane id="C1right1_2" sampledSeconds="294.89" traveltime="3.52" overlapTraveltime="3.64" density="2.46" laneDensity="2.46" occupancy="1.19" waitingTime="0.00" speed="37.93" departed="0" arrived="82" entered="82" left="0" laneChangedFrom="3" laneChangedTo="3"/>
            <lane id="C1right1_3" sampledSeconds="231.96" traveltime="3.43" overlapTraveltime="3.54" density="1.93" laneDensity="1.93" occupancy="0.93" waitingTime="0.00" speed="38.99" departed="0" arrived="64" entered="67" left="0" laneChangedFrom="3" laneChangedTo="0"/>
        </edge>
        <edge id="C2B2">
            <lane id="C2B2_0" sampledSeconds="0.00" departed="0" arrived="0" entered="0" left="0" laneChangedFrom="0" laneChangedTo="0"/>
            <lane id="C2B2_1" sampledSeconds="0.00" departed="0" arrived="0" entered="0" left="0" laneChangedFrom="0" laneChangedTo="0"/>
            <lane id="C2B2_2" sampledSeconds="0.00" departed="0" arrived="0" entered="0" left="0" laneChangedFrom="0" laneChangedTo="0"/>
            <lane id="C2B2_3" sampledSeconds="0.00" departed="0" arrived="0" entered="0" left="0" laneChangedFrom="0" laneChangedTo="0"/>
        </edge>
        <edge id="C2C1">
            <lane id="C2C1_0" sampledSeconds="356.18" traveltime="5.72" overlapTraveltime="5.92" density="3.40" laneDensity="3.40" occupancy="1.62" waitingTime="0.00" speed="20.52" departed="0" arrived="0" entered="61" left="60" laneChangedFrom="1" laneChangedTo="0"/>
            <lane id="C2C1_1" sampledSeconds="454.27" traveltime="5.43" overlapTraveltime="5.62" density="4.34" laneDensity="4.34" occupancy="2.07" waitingTime="0.00" speed="21.59" departed="0" arrived="0" entered="79" left="81" laneChangedFrom="0" laneChangedTo="2"/>
            <lane id="C2C1_2" sampledSeconds="457.01" traveltime="5.38" overlapTraveltime="5.57" density="4.36" laneDensity="4.36" occupancy="2.08" waitingTime="0.00" speed="21.78" departed="0" arrived="0" entered="83" left="82" laneChangedFrom="1" laneChangedTo="0"/>
            <lane id="C2C1_3" sampledSeconds="428.23" traveltime="5.37" overlapTraveltime="5.56" density="4.09" laneDensity="4.09" occupancy="1.95" waitingTime="0.00" speed="21.83" departed="0" arrived="0" entered="77" left="77" laneChangedFrom="0" laneChangedTo="0"/>
        </edge>
        <edge id="C2right2">
            <lane id="C2right2_0" sampledSeconds="286.39" traveltime="3.71" overlapTraveltime="3.84" density="2.39" laneDensity="2.39" occupancy="1.15" waitingTime="0.00" speed="35.97" departed="0" arrived="74" entered="75" left="0" laneChangedFrom="0" laneChangedTo="0"/>
            <lane id="C2right2_1" sampledSeconds="291.00" traveltime="3.95" overlapTraveltime="4.08" density="2.43" laneDensity="2.43" occupancy="1.17" waitingTime="0.00" speed="33.85" departed="0" arrived="72" entered="70" left="0" laneChangedFrom="0" laneChangedTo="2"/>
            <lane id="C2right2_2" sampledSeconds="325.73" traveltime="3.87" overlapTraveltime="4.00" density="2.72" laneDensity="2.72" occupancy="1.31" waitingTime="0.00" speed="34.54" departed="0" arrived="83" entered="82" left="0" laneChangedFrom="2" laneChangedTo="2"/>
            <lane id="C2right2_3" sampledSeconds="267.70" traveltime="3.59" overlapTraveltime="3.71" density="2.23" laneDensity="2.23" occupancy="1.08" waitingTime="0.00" speed="37.26" departed="0" arrived="71" entered="73" left="0" laneChangedFrom="2" laneChangedTo="0"/>
        </edge>
        <edge id="C2top2">
            <lane id="C2top2_0" sampledSeconds="0.00" departed="0" arrived="0" entered="0" left="0" laneChangedFrom="0" laneChangedTo="0"/>
            <lane id="C2top2_1" sampledSeconds="0.00" departed="0" arrived="0" entered="0" left="0" laneChangedFrom="0" laneChangedTo="0"/>
            <lane id="C2top2_2" sampledSeconds="0.00" departed="0" arrived="0" entered="0" left="0" laneChangedFrom="0" laneChangedTo="0"/>
            <lane id="C2top2_3" sampledSeconds="0.00" departed="0" arrived="0" entered="0" left="0" laneChangedFrom="0" laneChangedTo="0"/>
        </edge>
        <edge id="bottom0A0">
            <lane id="bottom0A0_0" sampledSeconds="0.00" departed="0" arrived="0" entered="0" left="0" laneChangedFrom="0" laneChangedTo="0"/>
            <lane id="bottom0A0_1" sampledSeconds="0.00" departed="0" arrived="0" entered="0" left="0" laneChangedFrom="0" laneChangedTo="0"/>
            <lane id="bottom0A0_2" sampledSeconds="0.00" departed="0" arrived="0" entered="0" left="0" laneChangedFrom="0" laneChangedTo="0"/>
            <lane id="bottom0A0_3" sampledSeconds="0.00" departed="0" arrived="0" entered="0" left="0" laneChangedFrom="0" laneChangedTo="0"/>
        </edge>
        <edge id="bottom1B0">
            <lane id="bottom1B0_0" sampledSeconds="0.00" departed="0" arrived="0" entered="0" left="0" laneChangedFrom="0" laneChangedTo="0"/>
            <lane id="bottom1B0_1" sampledSeconds="0.00" departed="0" arrived="0" entered="0" left="0" laneChangedFrom="0" laneChangedTo="0"/>
            <lane id="bottom1B0_2" sampledSeconds="0.00" departed="0" arrived="0" entered="0" left="0" laneChangedFrom="0" laneChangedTo="0"/>
            <lane id="bottom1B0_3" sampledSeconds="0.00" departed="0" arrived="0" entered="0" left="0" laneChangedFrom="0" laneChangedTo="0"/>
        </edge>
        <edge id="bottom2C0">
            <lane id="bottom2C0_0" sampledSeconds="0.00" departed="0" arrived="0" entered="0" left="0" laneChangedFrom="0" laneChangedTo="0"/>
            <lane id="bottom2C0_1" sampledSeconds="0.00" departed="0" arrived="0" entered="0" left="0" laneChangedFrom="0" laneChangedTo="0"/>
            <lane id="bottom2C0_2" sampledSeconds="0.00" departed="0" arrived="0" entered="0" left="0" laneChangedFrom="0" laneChangedTo="0"/>
            <lane id="bottom2C0_3" sampledSeconds="0.00" departed="0" arrived="0" entered="0" left="0" laneChangedFrom="0" laneChangedTo="0"/>
        </edge>
        <edge id="left0A0">
            <lane id="left0A0_0" sampledSeconds="1733.54" traveltime="26.70" overlapTraveltime="27.28" density="14.46" laneDensity="14.46" occupancy="7.15" waitingTime="715.00" speed="5.07" departed="68" arrived="0" entered="0" left="71" laneChangedFrom="8" laneChangedTo="13"/>
            <lane id="left0A0_1" sampledSeconds="2102.78" traveltime="27.85" overlapTraveltime="28.53" density="17.54" laneDensity="17.54" occupancy="8.69" waitingTime="880.00" speed="4.84" departed="85" arrived="0" entered="0" left="66" laneChangedFrom="32" laneChangedTo="14"/>
            <lane id="left0A0_2" sampledSeconds="2081.70" traveltime="27.17" overlapTraveltime="27.73" density="17.36" laneDensity="17.36" occupancy="8.59" waitingTime="874.00" speed="4.98" departed="73" arrived="0" entered="0" left="78" laneChangedFrom="26" laneChangedTo="29"/>
            <lane id="left0A0_3" sampledSeconds="2057.66" traveltime="26.44" overlapTraveltime="26.93" density="17.16" laneDensity="17.16" occupancy="8.49" waitingTime="854.00" speed="5.13" departed="74" arrived="0" entered="0" left="85" laneChangedFrom="10" laneChangedTo="20"/>
        </edge>
        <edge id="left1A1">
            <lane id="left1A1_0" sampledSeconds="1993.12" traveltime="28.11" overlapTraveltime="28.73" density="16.63" laneDensity="16.63" occupancy="8.23" waitingTime="867.00" speed="4.81" departed="80" arrived="0" entered="0" left="69" laneChangedFrom="17" laneChangedTo="7"/>
            <lane id="left1A1_1" sampledSeconds="2260.44" traveltime="27.17" overlapTraveltime="27.75" density="18.86" laneDensity="18.86" occupancy="9.34" waitingTime="958.00" speed="4.98" departed="82" arrived="0" entered="0" left="81" laneChangedFrom="23" laneChangedTo="21"/>
            <lane id="left1A1_2" sampledSeconds="2033.97" traveltime="27.20" overlapTraveltime="27.74" density="16.97" laneDensity="16.97" occupancy="8.39" waitingTime="855.00" speed="4.98" departed="78" arrived="0" entered="0" left="79" laneChangedFrom="24" laneChangedTo="25"/>
            <lane id="left1A1_3" sampledSeconds="1898.72" traveltime="28.77" overlapTraveltime="29.31" density="15.84" laneDensity="15.84" occupancy="7.84" waitingTime="831.00" speed="4.72" departed="60" arrived="0" entered="0" left="72" laneChangedFrom="9" laneChangedTo="20"/>
        </edge>
        <edge id="left2A2">
            <lane id="left2A2_0" sampledSeconds="1979.49" traveltime="28.45" overlapTraveltime="29.05" density="16.51" laneDensity="16.51" occupancy="8.17" waitingTime="891.00" speed="4.76" departed="76" arrived="0" entered="0" left="69" laneChangedFrom="16" laneChangedTo="10"/>
            <lane id="left2A2_1" sampledSeconds="2090.31" traveltime="27.01" overlapTraveltime="27.60" density="17.44" laneDensity="17.44" occupancy="8.63" waitingTime="883.00" speed="5.01" departed="80" arrived="0" entered="0" left="76" laneChangedFrom="25" laneChangedTo="21"/>
            <lane id="left2A2_2" sampledSeconds="1957.26" traveltime="27.51" overlapTraveltime="28.04" density="16.33" laneDensity="16.33" occupancy="8.08" waitingTime="804.00" speed="4.93" departed="72" arrived="0" entered="0" left="77" laneChangedFrom="19" laneChangedTo="23"/>
            <lane id="left2A2_3" sampledSeconds="1958.62" traveltime="25.47" overlapTraveltime="26.02" density="16.34" laneDensity="16.34" occupancy="8.08" waitingTime="777.00" speed="5.31" departed="72" arrived="0" entered="0" left="78" laneChangedFrom="8" laneChangedTo="14"/>
        </edge>
        <edge id="right0C0">
            <lane id="right0C0_0" sampledSeconds="0.00" departed="0" arrived="0" entered="0" left="0" laneChangedFrom="0" laneChangedTo="0"/>
            <lane id="right0C0_1" sampledSeconds="0.00" departed="0" arrived="0" entered="0" left="0" laneChangedFrom="0" laneChangedTo="0"/>
            <lane id="right0C0_2" sampledSeconds="0.00" departed="0" arrived="0" entered="0" left="0" laneChangedFrom="0" laneChangedTo="0"/>
            <lane id="right0C0_3" sampledSeconds="0.00" departed="0" arrived="0" entered="0" left="0" laneChangedFrom="0" laneChangedTo="0"/>
        </edge>
        <edge id="right1C1">
            <lane id="right1C1_0" sampledSeconds="0.00" departed="0" arrived="0" entered="0" left="0" laneChangedFrom="0" laneChangedTo="0"/>
            <lane id="right1C1_1" sampledSeconds="0.00" departed="0" arrived="0" entered="0" left="0" laneChangedFrom="0" laneChangedTo="0"/>
            <lane id="right1C1_2" sampledSeconds="0.00" departed="0" arrived="0" entered="0" left="0" laneChangedFrom="0" laneChangedTo="0"/>
            <lane id="right1C1_3" sampledSeconds="0.00" departed="0" arrived="0" entered="0" left="0" laneChangedFrom="0" laneChangedTo="0"/>
        </edge>
        <edge id="right2C2">
            <lane id="right2C2_0" sampledSeconds="0.00" departed="0" arrived="0" entered="0" left="0" laneChangedFrom="0" laneChangedTo="0"/>
            <lane id="right2C2_1" sampledSeconds="0.00" departed="0" arrived="0" entered="0" left="0" laneChangedFrom="0" laneChangedTo="0"/>
            <lane id="right2C2_2" sampledSeconds="0.00" departed="0" arrived="0" entered="0" left="0" laneChangedFrom="0" laneChangedTo="0"/>
            <lane id="right2C2_3" sampledSeconds="0.00" departed="0" arrived="0" entered="0" left="0" laneChangedFrom="0" laneChangedTo="0"/>
        </edge>
        <edge id="top0A2">
            <lane id="top0A2_0" sampledSeconds="1462.59" traveltime="28.14" overlapTraveltime="28.63" density="12.20" laneDensity="12.20" occupancy="6.03" waitingTime="642.00" speed="4.83" departed="54" arrived="0" entered="0" left="64" laneChangedFrom="6" laneChangedTo="17"/>
            <lane id="top0A2_1" sampledSeconds="2149.47" traveltime="26.52" overlapTraveltime="27.17" density="17.93" laneDensity="17.93" occupancy="8.88" waitingTime="853.00" speed="5.09" departed="86" arrived="0" entered="0" left="71" laneChangedFrom="24" laneChangedTo="11"/>
            <lane id="top0A2_2" sampledSeconds="2092.61" traveltime="27.54" overlapTraveltime="28.10" density="17.46" laneDensity="17.46" occupancy="8.64" waitingTime="864.00" speed="4.92" departed="77" arrived="0" entered="0" left="78" laneChangedFrom="19" laneChangedTo="19"/>
            <lane id="top0A2_3" sampledSeconds="2306.28" traveltime="26.85" overlapTraveltime="27.38" density="19.24" laneDensity="19.24" occupancy="9.53" waitingTime="966.00" speed="5.05" departed="83" arrived="0" entered="0" left="87" laneChangedFrom="12" laneChangedTo="14"/>
        </edge>
        <edge id="top1B2">
            <lane id="top1B2_0" sampledSeconds="1081.17" traveltime="23.85" overlapTraveltime="24.73" density="9.02" laneDensity="9.02" occupancy="4.46" waitingTime="302.00" speed="5.59" departed="79" arrived="0" entered="0" left="29" laneChangedFrom="61" laneChangedTo="9"/>
            <lane id="top1B2_1" sampledSeconds="3670.82" traveltime="36.95" overlapTraveltime="37.55" density="30.62" laneDensity="30.62" occupancy="15.17" waitingTime="1814.00" speed="3.68" departed="81" arrived="0" entered="0" left="107" laneChangedFrom="50" laneChangedTo="75"/>
            <lane id="top1B2_2" sampledSeconds="3755.76" traveltime="35.17" overlapTraveltime="36.03" density="31.33" laneDensity="31.33" occupancy="15.47" waitingTime="1744.00" speed="3.84" departed="68" arrived="0" entered="0" left="108" laneChangedFrom="76" laneChangedTo="118"/>
            <lane id="top1B2_3" sampledSeconds="2021.09" traveltime="46.52" overlapTraveltime="47.00" density="16.86" laneDensity="16.86" occupancy="8.34" waitingTime="1036.00" speed="2.94" departed="72" arrived="0" entered="0" left="56" laneChangedFrom="77" laneChangedTo="62"/>
        </edge>
        <edge id="top2C2">
            <lane id="top2C2_0" sampledSeconds="1800.46" traveltime="28.07" overlapTraveltime="28.74" density="15.02" laneDensity="15.02" occupancy="7.43" waitingTime="788.00" speed="4.81" departed="73" arrived="0" entered="0" left="60" laneChangedFrom="16" laneChangedTo="5"/>
            <lane id="top2C2_1" sampledSeconds="2069.37" traveltime="26.16" overlapTraveltime="26.71" density="17.26" laneDensity="17.26" occupancy="8.54" waitingTime="856.00" speed="5.17" departed="79" arrived="0" entered="0" left="80" laneChangedFrom="23" laneChangedTo="25"/>
            <lane id="top2C2_2" sampledSeconds="2087.70" traveltime="26.55" overlapTraveltime="27.09" density="17.41" laneDensity="17.41" occupancy="8.62" waitingTime="840.00" speed="5.10" departed="79" arrived="0" entered="0" left="82" laneChangedFrom="23" laneChangedTo="26"/>
            <lane id="top2C2_3" sampledSeconds="2029.40" traveltime="27.70" overlapTraveltime="28.23" density="16.93" laneDensity="16.93" occupancy="8.38" waitingTime="880.00" speed="4.89" departed="69" arrived="0" entered="0" left="78" laneChangedFrom="8" laneChangedTo="14"/>
        </edge>
    </interval>
</meandata>
